slowgrad/__init__.py
slowgrad/layers.py
slowgrad/ops.py
slowgrad/optim.py
slowgrad/tensor.py
slowgrad/test.py
slowgrad/utils.py
slowgrad-0.2.0.dist-info/LICENSE
slowgrad-0.2.0.dist-info/METADATA
slowgrad-0.2.0.dist-info/WHEEL
slowgrad-0.2.0.dist-info/top_level.txt
slowgrad-0.2.0.dist-info/RECORD
