Metadata-Version: 2.1
Name: slowgrad
Version: 0.2.0
Summary: Take it slow, compute gradients
Home-page: UNKNOWN
Author: Daniele Paliotta
License: MIT
Platform: UNKNOWN
Classifier: Programming Language :: Python :: 3
Classifier: License :: OSI Approved :: MIT License
Requires-Python: >=3.7
Requires-Dist: numpy
Requires-Dist: tqdm
